{
    "generation": 6,
    "primaryType": "PSYCHIC",
    "secondaryType": "UNKNOWN",
    "moves": [
        [
            1,
            "SCRATCH"
        ],
        [
            1,
            "LEER"
        ],
        [
            3,
            "FAKEOUT"
        ],
        [
            6,
            "DISARMINGVOICE"
        ],
        [
            9,
            "CONFUSION"
        ],
        [
            18,
            "COVET"
        ],
        [
            21,
            "PSYBEAM"
        ],
        [
            30,
            "LIGHTSCREEN"
        ],
        [
            30,
            "REFLECT"
        ],
        [
            33,
            "PSYSHOCK"
        ]
    ],
    "tutorMoves": [
        "ALLYSWITCH",
        "ATTRACT",
        "CALMMIND",
        "CAPTIVATE",
        "CHARGEBEAM",
        "CONFIDE",
        "COVET",
        "CUT",
        "DARKPULSE",
        "DOUBLETEAM",
        "DREAMEATER",
        "ECHOEDVOICE",
        "ENDURE",
        "ENERGYBALL",
        "EXPANDINGFORCE",
        "FACADE",
        "FAKETEARS",
        "FLASH",
        "FRUSTRATION",
        "GRAVITY",
        "HEALBELL",
        "HELPINGHAND",
        "HIDDENPOWER",
        "IRONTAIL",
        "LIGHTSCREEN",
        "MAGICCOAT",
        "MAGICROOM",
        "MIMIC",
        "NASTYPLOT",
        "NATURALGIFT",
        "PAYBACK",
        "PAYDAY",
        "PLAYROUGH",
        "PROTECT",
        "PSYCHIC",
        "PSYCHUP",
        "PSYSHOCK",
        "RAINDANCE",
        "RECYCLE",
        "REFLECT",
        "REST",
        "RETURN",
        "ROLEPLAY",
        "ROUND",
        "SAFEGUARD",
        "SECRETPOWER",
        "SHOCKWAVE",
        "SIGNALBEAM",
        "SKILLSWAP",
        "SLEEPTALK",
        "SNATCH",
        "SNORE",
        "SUBSTITUTE",
        "SUNNYDAY",
        "SWAGGER",
        "SWIFT",
        "TELEKINESIS",
        "THUNDERBOLT",
        "THUNDERWAVE",
        "TORMENT",
        "TOXIC",
        "TRICK",
        "TRICKROOM",
        "WONDERROOM",
        "WORKUP",
        "ZENHEADBUTT"
    ],
    "eggMoves": [
        "TICKLE",
        "YAWN"
    ],
    "height": 0.3,
    "weight": 3.5,
    "abilities": [
        "KEENEYE",
        "INFILTRATOR"
    ],
    "hiddenAbilitie": [
        "OWNTEMPO"
    ],
    "baseTotal": 355,
    "baseStats": [
        62,
        48,
        54,
        68,
        63,
        60
    ],
    "flags": [],
    "name": "Espurr",
    "species": "ESPURR",
    "catchRate": 190,
    "happiness": 50,
    "baseExp": 71,
    "evs": [
        "SPEED",
        1
    ],
    "growthRate": "MEDIUM_FAST",
    "genderRatio": 50,
    "forms": [],
    "internationalPokedex": 677
}