{
    "generation": 5,
    "primaryType": "WATER",
    "secondaryType": "UNKNOWN",
    "moves": [
        [
            1,
            "LEER"
        ],
        [
            1,
            "LICK"
        ],
        [
            1,
            "FURYSWIPES"
        ],
        [
            1,
            "SCALD"
        ]
    ],
    "tutorMoves": [
        "ACROBATICS",
        "AQUATAIL",
        "ATTRACT",
        "BLIZZARD",
        "BRICKBREAK",
        "CAPTIVATE",
        "CONFIDE",
        "COVET",
        "CUT",
        "DIG",
        "DIVE",
        "DOUBLETEAM",
        "ENDEAVOR",
        "ENDURE",
        "FACADE",
        "FLING",
        "FOCUSBLAST",
        "FOCUSPUNCH",
        "FRUSTRATION",
        "GASTROACID",
        "GIGAIMPACT",
        "GRASSKNOT",
        "GUNKSHOT",
        "HAIL",
        "HELPINGHAND",
        "HIDDENPOWER",
        "HONECLAWS",
        "HYPERBEAM",
        "ICEBEAM",
        "ICEPUNCH",
        "ICYWIND",
        "IRONTAIL",
        "KNOCKOFF",
        "LOWKICK",
        "LOWSWEEP",
        "MIMIC",
        "NATURALGIFT",
        "PAYBACK",
        "POWERUPPUNCH",
        "PROTECT",
        "RAINDANCE",
        "RECYCLE",
        "REST",
        "RETURN",
        "ROCKSLIDE",
        "ROCKSMASH",
        "ROCKTOMB",
        "ROLEPLAY",
        "ROUND",
        "SCALD",
        "SECRETPOWER",
        "SHADOWCLAW",
        "SLEEPTALK",
        "SNORE",
        "SUBSTITUTE",
        "SUPERPOWER",
        "SURF",
        "SWAGGER",
        "TAUNT",
        "THIEF",
        "THROATCHOP",
        "TORMENT",
        "TOXIC",
        "UPROAR",
        "WATERFALL",
        "WATERPLEDGE",
        "WATERPULSE",
        "WORKUP"
    ],
    "eggMoves": [],
    "height": 1.0,
    "weight": 29.0,
    "abilities": [
        "GLUTTONY"
    ],
    "hiddenAbilitie": [
        "TORRENT"
    ],
    "baseTotal": 498,
    "baseStats": [
        75,
        98,
        63,
        101,
        98,
        63
    ],
    "flags": [],
    "name": "Simipour",
    "species": "SIMIPOUR",
    "catchRate": 75,
    "happiness": 50,
    "baseExp": 174,
    "evs": [
        "SPEED",
        2
    ],
    "growthRate": "MEDIUM_FAST",
    "genderRatio": 12.5,
    "forms": [],
    "internationalPokedex": 516
}