{
    "move": "BODYPRESS",
    "name": "Plancha Corporal",
    "type": "FIGHTING",
    "power": 80,
    "accuracy": 100,
    "totalPP": 10,
    "priority": 0,
    "target": "NearOther",
    "effectChance": 0,
    "functionCode": "UseUserDefenseInsteadOfUserAttack",
    "flags": [
        "Contact",
        "CanProtect",
        "CanMirrorMove",
        "CannotMetronome"
    ],
    "description": "El usuario embistie al objetivo. Cuanto m치s alta sea la Defensa del usuario m치s da침o inflingir치.",
    "category": "Physical"
}